<?xml version="1.0"?>
<opencv_storage>
<cascade>
  <stageType>BOOST</stageType>
  <featureType>HAAR</featureType>
  <height>24</height>
  <width>24</width>
  <stageParams>
    <boostType>GAB</boostType>
    <minHitRate>9.9500000476837158e-01</minHitRate>
    <maxFalseAlarm>5.0000000000000000e-01</maxFalseAlarm>
    <weightTrimRate>9.4999999999999996e-01</weightTrimRate>
    <maxDepth>1</maxDepth>
    <maxWeakCount>100</maxWeakCount></stageParams>
  <featureParams>
    <maxCatCount>0</maxCatCount>
    <featSize>1</featSize>
    <mode>BASIC</mode></featureParams>
  <stageNum>4</stageNum>
  <stages>
    <!-- stage 0 -->
    <_>
      <maxWeakCount>1</maxWeakCount>
      <stageThreshold>9.8131901025772095e-01</stageThreshold>
      <weakClassifiers>
        <_>
          <internalNodes>
            0 -1 3 1.3190907426178455e-02</internalNodes>
          <leafValues>
            -1. 9.8131901025772095e-01</leafValues></_></weakClassifiers></_>
    <!-- stage 1 -->
    <_>
      <maxWeakCount>1</maxWeakCount>
      <stageThreshold>9.6021294593811035e-01</stageThreshold>
      <weakClassifiers>
        <_>
          <internalNodes>
            0 -1 0 1.2805579602718353e-01</internalNodes>
          <leafValues>
            -9.9412626028060913e-01 9.6021294593811035e-01</leafValues></_></weakClassifiers></_>
    <!-- stage 2 -->
    <_>
      <maxWeakCount>2</maxWeakCount>
      <stageThreshold>-1.7334939911961555e-02</stageThreshold>
      <weakClassifiers>
        <_>
          <internalNodes>
            0 -1 1 -3.3457770943641663e-02</internalNodes>
          <leafValues>
            9.6762281656265259e-01 -9.0123456716537476e-01</leafValues></_>
        <_>
          <internalNodes>
            0 -1 5 -4.1006918763741851e-05</internalNodes>
          <leafValues>
            -8.1363087892532349e-01 8.8389962911605835e-01</leafValues></_></weakClassifiers></_>
    <!-- stage 3 -->
    <_>
      <maxWeakCount>2</maxWeakCount>
      <stageThreshold>-9.0847559273242950e-02</stageThreshold>
      <weakClassifiers>
        <_>
          <internalNodes>
            0 -1 2 3.0614063143730164e-02</internalNodes>
          <leafValues>
            -9.0461540222167969e-01 9.2722225189208984e-01</leafValues></_>
        <_>
          <internalNodes>
            0 -1 4 3.9704278606222942e-05</internalNodes>
          <leafValues>
            8.1376785039901733e-01 -8.2945692539215088e-01</leafValues></_></weakClassifiers></_></stages>
  <features>
    <_>
      <rects>
        <_>
          1 0 20 12 -1.</_>
        <_>
          1 6 20 6 2.</_></rects>
      <tilted>0</tilted></_>
    <_>
      <rects>
        <_>
          3 14 18 2 -1.</_>
        <_>
          9 14 6 2 3.</_></rects>
      <tilted>0</tilted></_>
    <_>
      <rects>
        <_>
          9 10 12 6 -1.</_>
        <_>
          9 10 6 3 2.</_>
        <_>
          15 13 6 3 2.</_></rects>
      <tilted>0</tilted></_>
    <_>
      <rects>
        <_>
          9 11 6 3 -1.</_>
        <_>
          11 11 2 3 3.</_></rects>
      <tilted>0</tilted></_>
    <_>
      <rects>
        <_>
          10 11 2 1 -1.</_>
        <_>
          11 11 1 1 2.</_></rects>
      <tilted>0</tilted></_>
    <_>
      <rects>
        <_>
          12 11 2 1 -1.</_>
        <_>
          13 11 1 1 2.</_></rects>
      <tilted>0</tilted></_></features></cascade>
</opencv_storage>
